advanced_led_control/__init__.py
advanced_led_control/led_controller.py
advanced_led_control/settings.py
advanced_led_control/models/Indicator.py
advanced_led_control/models/Procedure.py
advanced_led_control/models/ValueIndication.py
advanced_led_control/models/__init__.py
advanced_led_control/models/color_types.py
advanced_led_control/models/colors.py
advanced_led_control/models/internal_modes.py
advanced_led_control/models/leds.py
advanced_led_control/models/modes.py
advanced_led_control/tests/__init__.py
advanced_led_control/tests/cpu_and_ram.py
advanced_led_control/tests/test.py
advanced_led_control/tests/test_sync.py
advanced_led_control/utils/GracefulKiller.py
advanced_led_control/utils/__init__.py
advanced_led_control/utils/internal.py
advanced_led_control/utils/sync_run.py
advanced_led_control-0.3.1.dist-info/LICENSE
advanced_led_control-0.3.1.dist-info/METADATA
advanced_led_control-0.3.1.dist-info/WHEEL
advanced_led_control-0.3.1.dist-info/top_level.txt
advanced_led_control-0.3.1.dist-info/RECORD
