Metadata-Version: 2.1
Name: advanced-led-control
Version: 0.3.1
Summary: An non-official advanced controller for blinkstick
Home-page: https://github.com/weshouman/advanced-led-control
Author: Walid Shouman
Author-email: eng.walidshouman@gmail.com
License: UNKNOWN
Platform: UNKNOWN
Classifier: Programming Language :: Python :: 3
Classifier: License :: OSI Approved :: MIT License
Classifier: Operating System :: OS Independent
Requires-Python: >=3.5.2
Requires-Dist: BlinkStick (==1.1.8)
